kaiju_scheduler/__init__.py
kaiju_scheduler/interfaces.py
kaiju_scheduler/py.typed
kaiju_scheduler/scheduler.py
kaiju_scheduler/server.py
kaiju_scheduler/utils.py
kaiju_scheduler-0.1.4.dist-info/LICENSE
kaiju_scheduler-0.1.4.dist-info/METADATA
kaiju_scheduler-0.1.4.dist-info/WHEEL
kaiju_scheduler-0.1.4.dist-info/top_level.txt
kaiju_scheduler-0.1.4.dist-info/RECORD
